{
  "packageName": "Zooz ZAC36 Titan Valve Actuator",
  "author": "Jeff Page (@jtp10181)",
  "minimumHEVersion": "2.3.4",
  "dateReleased": "2024-03-01",
  "documentationLink": "https://github.com/jtp10181/Hubitat/tree/main/Drivers/zooz",
  "communityLink": "https://community.hubitat.com/t/zooz-zac36/79426",
  "releaseNotes": "Version [1.0.2] - 2024-03-01\n  - Update library code\n  - Add paramaters 113, 114 and 115 for battery configuration\n  - Add support for battery v2 disconnected/charging status\n  - Fixed refresh setting wrong state, removed valve notification from refresh (uses switch state)\n  - Changed battery and powersource reporting defaults to enabled\n  - Changed invert switch default to be disabled (per recomendation from Zooz)\n",
  "version": "1.0.2",
  "drivers": [
    {
      "id": "f514baca-a796-4f7e-90cc-7f29132a0e0d",
      "name": "Zooz ZAC36 Titan Valve Actuator",
      "namespace": "jtp10181",
      "location": "https://jtp10181.gateway.scarf.sh/zooz-zac36-v1.0.2.groovy",
      "required": true
    }
  ]
}
